cryptoAuth/__init__.py
cryptoAuth/admin.py
cryptoAuth/apps.py
cryptoAuth/models.py
cryptoAuth/tests.py
cryptoAuth/urls.py
cryptoAuth/views.py
cryptoAuth/migrations/0001_initial.py
cryptoAuth/migrations/__init__.py
dj_crypto_auth-1.0.dist-info/LICENSE
dj_crypto_auth-1.0.dist-info/METADATA
dj_crypto_auth-1.0.dist-info/WHEEL
dj_crypto_auth-1.0.dist-info/top_level.txt
dj_crypto_auth-1.0.dist-info/RECORD
